django_assistant/__init__.py
django_assistant/admin.py
django_assistant/apps.py
django_assistant/models.py
django_assistant/tests.py
django_assistant/urls.py
django_assistant/views.py
django_assistant/migrations/0001_initial.py
django_assistant/migrations/__init__.py
django_assistant/static/django_assistant/index.css
django_assistant/static/django_assistant/index.js
django_assistant/static/django_assistant/chosen/chosen-sprite.png
django_assistant/static/django_assistant/chosen/chosen-sprite@2x.png
django_assistant/static/django_assistant/chosen/chosen.css
django_assistant/static/django_assistant/chosen/chosen.jquery.js
django_assistant/static/django_assistant/js/bootstrap-select.js
django_assistant/static/django_assistant/js/bootstrap-switch.js
django_assistant/static/django_assistant/js/bootstrap.js
django_assistant/static/django_assistant/js/chosen.css
django_assistant/static/django_assistant/js/jquery-1.7.2.min.js
django_assistant/static/django_assistant/js/jquery-ui.js
django_assistant/static/django_assistant/js/jquery.contentcarousel.js
django_assistant/static/django_assistant/js/jquery.contentcarousel.js.bak
django_assistant/static/django_assistant/js/chosen/chosen.jquery.js
django_assistant/static/django_assistant/js/notify/bootstrap-notify.js
django_assistant/static/django_assistant/style/bootstrap-select.css
django_assistant/static/django_assistant/style/bootstrap-switch.css
django_assistant/static/django_assistant/style/bootstrap-switch.min.css
django_assistant/static/django_assistant/style/bootstrap-theme.css
django_assistant/static/django_assistant/style/bootstrap.css
django_assistant/static/django_assistant/style/bootstrap.css.map
django_assistant/static/django_assistant/style/code-base.css
django_assistant/static/django_assistant/style/font-awesome.min.css
django_assistant/static/django_assistant/style/jquery-ui.css
django_assistant/static/django_assistant/style/jquery.jscrollpane.css
django_assistant-1.0.3.dist-info/DESCRIPTION.rst
django_assistant-1.0.3.dist-info/METADATA
django_assistant-1.0.3.dist-info/RECORD
django_assistant-1.0.3.dist-info/WHEEL
django_assistant-1.0.3.dist-info/metadata.json
django_assistant-1.0.3.dist-info/top_level.txt
